<?xml version="1.0" encoding="UTF-8"?>
<beans xmlns="http://www.springframework.org/schema/beans"
       xmlns:xsi="http://www.w3.org/2001/XMLSchema-instance"
       xmlns:dubbo="http://dubbo.apache.org/schema/dubbo" xmlns:context="http://www.springframework.org/schema/context"
       xsi:schemaLocation="http://www.springframework.org/schema/beans
       http://www.springframework.org/schema/beans/spring-beans-4.3.xsd
       http://dubbo.apache.org/schema/dubbo
       http://dubbo.apache.org/schema/dubbo/dubbo.xsd http://www.springframework.org/schema/context http://www.springframework.org/schema/context/spring-context.xsd">

    <!-- 提供方应用信息，用于计算依赖关系 -->
    <dubbo:application name="user-service-provider">
        <dubbo:parameter key="qos.enable" value="true"/>
        <dubbo:parameter key="qos.accept.foreign.ip" value="false"/>
        <dubbo:parameter key="qos.port" value="22223"/>
    </dubbo:application>

    <!-- 使用multicast广播注册中心暴露服务地址 -->
    <!--<dubbo:registry address="zookeeper://zookeeper.kingsley.com:2181"/>-->
    <dubbo:registry protocol="zookeeper" address="zookeeper.kingsley.com:2181"/>

    <!-- 元数据配置 -->
    <dubbo:metadata-report address="zookeeper://zookeeper.kingsley.com:2181" />

    <!-- 用dubbo协议在20880端口暴露服务,指定通信规则(通信协议和端口) -->
    <dubbo:protocol name="dubbo" port="20880"/>

    <!-- 声明需要暴露的服务接口 -->
    <dubbo:service interface="com.kingsley.study.dubbo.service.UserService" ref="userServiceImpl"/>

    <dubbo:service interface="com.kingsley.study.dubbo.service.MemberInfoService" ref="memberInfoServiceImpl"/>

    <context:component-scan base-package="com.kingsley.study.dubbo.service"/>

</beans>